typed_singleton/__init__.py
typed_singleton/py.typed
typed_singleton/typed_singleton.py
typed_singleton-0.1.2.dist-info/LICENSE.txt
typed_singleton-0.1.2.dist-info/METADATA
typed_singleton-0.1.2.dist-info/WHEEL
typed_singleton-0.1.2.dist-info/RECORD
