Metadata-Version: 2.1
Name: typed_singleton
Version: 0.1.2
Summary: Package to provide a decorator to create singletons
Home-page: https://github.com/386jp/typed_singleton
License: MIT
Author: Kyosuke Miyamura
Author-email: ask@386.jp
Requires-Python: >=3.12,<4.0
Classifier: License :: OSI Approved :: MIT License
Classifier: Programming Language :: Python :: 3
Classifier: Programming Language :: Python :: 3.12
Project-URL: Repository, https://github.com/386jp/typed_singleton
